lib/__init__.py
lib/src/__init__.py
lib/src/hello.py
lib/tools/__init__.py
lib/tools/cli.py
python_setup/__init__.py
python_setup/src/__init__.py
python_setup/src/hello.py
python_setup/tools/__init__.py
python_setup/tools/cli.py
python_setup-0.1.4.dist-info/LICENSE
python_setup-0.1.4.dist-info/METADATA
python_setup-0.1.4.dist-info/WHEEL
python_setup-0.1.4.dist-info/entry_points.txt
python_setup-0.1.4.dist-info/top_level.txt
python_setup-0.1.4.dist-info/RECORD
