Metadata-Version: 2.1
Name: python-setup
Version: 0.1.4
Summary: A small example package
Home-page: https://github.com/zjykzj/python-setup.py
Author: zj
Author-email: wy163zhuj@163.com
License: UNKNOWN
Platform: UNKNOWN
Classifier: Programming Language :: Python :: 3
Classifier: Operating System :: OS Independent
Classifier: License :: OSI Approved :: Apache Software License
Requires-Python: >=3.6
